odoo/addons/coopdevs_meta_ux/README.md
odoo/addons/coopdevs_meta_ux/__init__.py
odoo/addons/coopdevs_meta_ux/__manifest__.py
odoo14_addon_coopdevs_meta_ux-14.0.1.0.0.dist-info/METADATA
odoo14_addon_coopdevs_meta_ux-14.0.1.0.0.dist-info/WHEEL
odoo14_addon_coopdevs_meta_ux-14.0.1.0.0.dist-info/top_level.txt
odoo14_addon_coopdevs_meta_ux-14.0.1.0.0.dist-info/RECORD
